bot7685_ext/__init__.py
bot7685_ext/_ext.abi3.so
bot7685_ext/_ext.pyi
bot7685_ext/wplace/__init__.py
bot7685_ext/wplace/compare.py
bot7685_ext/wplace/compose.py
bot7685_ext/wplace/consts.py
bot7685_ext/wplace/group.py
bot7685_ext/wplace/overlay.py
bot7685_ext-0.2.0.dist-info/METADATA
bot7685_ext-0.2.0.dist-info/WHEEL
bot7685_ext-0.2.0.dist-info/RECORD
