Metadata-Version: 2.4
Name: bot7685-ext
Version: 0.2.0
Summary: Extensions for Bot7685
Requires-Python: >=3.10
